CHANGES.rst
CONTRIBUTORS.rst
MANIFEST.in
README.rst
buildout.cfg
setup.cfg
setup.py
travis.cfg
docs/LICENSE.GPL
docs/LICENSE.rst
src/collective/__init__.py
src/collective.js.iframeresizer.egg-info/PKG-INFO
src/collective.js.iframeresizer.egg-info/SOURCES.txt
src/collective.js.iframeresizer.egg-info/dependency_links.txt
src/collective.js.iframeresizer.egg-info/entry_points.txt
src/collective.js.iframeresizer.egg-info/namespace_packages.txt
src/collective.js.iframeresizer.egg-info/not-zip-safe
src/collective.js.iframeresizer.egg-info/requires.txt
src/collective.js.iframeresizer.egg-info/top_level.txt
src/collective/js/__init__.py
src/collective/js/iframeresizer/__init__.py
src/collective/js/iframeresizer/configure.zcml
src/collective/js/iframeresizer/interfaces.py
src/collective/js/iframeresizer/setuphandlers.py
src/collective/js/iframeresizer/testing.py
src/collective/js/iframeresizer/testing.zcml
src/collective/js/iframeresizer/upgrades.zcml
src/collective/js/iframeresizer/browser/__init__.py
src/collective/js/iframeresizer/browser/configure.zcml
src/collective/js/iframeresizer/browser/overrides/.gitkeep
src/collective/js/iframeresizer/browser/static/.gitkeep
src/collective/js/iframeresizer/browser/static/ie8.polyfils.min.js
src/collective/js/iframeresizer/browser/static/iframeResizer.contentWindow.js
src/collective/js/iframeresizer/browser/static/iframeResizer.contentWindow.map
src/collective/js/iframeresizer/browser/static/iframeResizer.contentWindow.min.js
src/collective/js/iframeresizer/browser/static/iframeResizer.js
src/collective/js/iframeresizer/browser/static/iframeResizer.map
src/collective/js/iframeresizer/browser/static/iframeResizer.min.js
src/collective/js/iframeresizer/browser/static/index.js
src/collective/js/iframeresizer/locales/collective.js.iframeresizer.pot
src/collective/js/iframeresizer/locales/update.sh
src/collective/js/iframeresizer/profiles/default/browserlayer.xml
src/collective/js/iframeresizer/profiles/default/collectivejsiframeresizer_marker.txt
src/collective/js/iframeresizer/profiles/default/jsregistry.xml
src/collective/js/iframeresizer/profiles/default/metadata.xml
src/collective/js/iframeresizer/profiles/testing/collectivejsiframeresizer_testing.txt
src/collective/js/iframeresizer/profiles/testing/metadata.xml
src/collective/js/iframeresizer/tests/__init__.py
src/collective/js/iframeresizer/tests/test_robot.py
src/collective/js/iframeresizer/tests/test_setup.py
