Metadata-Version: 2.1
Name: collective.js.iframeresizer
Version: 0.4
Summary: Plone integration of iframe-resizer jquery plugin
Home-page: http://pypi.python.org/pypi/collective.js.iframeresizer
Author: Godefroid Chapelle
Author-email: gotcha@bubblenet.be
License: GPL
Keywords: Python Plone
Platform: UNKNOWN
Classifier: Environment :: Web Environment
Classifier: Framework :: Plone
Classifier: Framework :: Plone :: 4.3
Classifier: Programming Language :: Python
Classifier: Programming Language :: Python :: 2.7
Provides-Extra: test
